sisosign/__init__.py
sisosign/sisosign.py
sisosign-0.3.2.dist-info/entry_points.txt
sisosign-0.3.2.dist-info/LICENSE
sisosign-0.3.2.dist-info/WHEEL
sisosign-0.3.2.dist-info/METADATA
sisosign-0.3.2.dist-info/RECORD
