Metadata-Version: 2.1
Name: sisosign
Version: 0.3.2
Summary: A command-line tool for those times when you can't decide who should go.
License: MIT
Author: Eric Seidler
Author-email: eric.seidler@gmail.com
Requires-Python: >=3.7,<4.0
Classifier: License :: OSI Approved :: MIT License
Classifier: Operating System :: OS Independent
Classifier: Programming Language :: Python :: 3
Classifier: Programming Language :: Python :: 3.7
Classifier: Programming Language :: Python :: 3.8
Classifier: Programming Language :: Python :: 3.9
Classifier: Topic :: Utilities
Requires-Dist: click (>=8.0.1,<9.0.0)
Project-URL: Homepage, https://github.com/etseidler/sisosign
